{
  "version": 1,
  "metadata": {
    "description": "Synthetic trace #0100 - CPU: 18.3, Memory: 33.3GB, Replicas: 2"
  },
  "events": [
    {
      "ts": 1730390500,
      "applied_objs": [
        {
          "apiVersion": "apps/v1",
          "kind": "Deployment",
          "metadata": {
            "name": "web",
            "namespace": "default"
          },
          "spec": {
            "replicas": 2,
            "selector": {
              "matchLabels": {
                "app": "web"
              }
            },
            "template": {
              "metadata": {
                "labels": {
                  "app": "web"
                }
              },
              "spec": {
                "containers": [
                  {
                    "name": "web",
                    "image": "ghcr.io/example/web:1.0",
                    "resources": {
                      "requests": {
                        "cpu": "9.144680069321158",
                        "memory": "16.646401003591002Gi"
                      }
                    }
                  }
                ]
              }
            }
          }
        }
      ],
      "deleted_objs": []
    }
  ]
}